{"id":"dell-streak","name":"Dell Streak","description":"Introducing the Dell Streak, the 5\" go-anywhere pocket tablet. This perfectly-sized, go-anywhere entertainment, social connection and navigation device includes:\r\n\r\n• Widescreen display optimally designed for mobile web, video and movies\r\n• Integrated social networking widgets and apps, plus tons of apps through the Android™ Marketplace\r\n• Crystal-clear, scratch-resistant Gorilla® glass screen\r\n• Google Maps™ with navigation and text-to-voice, turn-by-turn directions with Street View\r\n• Multitasking Google Android OS that gives you the freedom to do what you want","availability":["O2 (United Kingdom)","AT&T (United States)","Optus (Australia)"],"battery":{"type":"Lithium Ion (Li-Ion) (1530 mAH)","talkTime":"7 hours","standbyTime":"400 hours"},"storage":{"ram":"512MB","flash":"2000MB"},"connectivity":{"cell":"Version 1: UMTS 2100/900  GSM/EDGE 1900/1800/900/850\r\nVersion 2: UMTS 2100/1900/850  GSM/EDGE 1900/1800/900/850","wifi":"802.11 b/g","bluetooth":"Bluetooth 2.1","infrared":false,"gps":true},"android":{"os":"Android 1.6","ui":""},"sizeAndWeight":{"dimensions":["152.9 mm (w)","79.1 mm (h)","9.98 mm (d)"],"weight":"220.0 grams"},"display":{"screenSize":"5.0 inches","screenResolution":"WVGA (800 x 480)","touchScreen":true},"hardware":{"fmRadio":false,"physicalKeyboard":"/phone/static/images/False.png","accelerometer":true,"cpu":"1 GHz Qualcomm Snapdragon QSD8250","usb":"USB 2.0","audioJack":"3.5mm"},"camera":{"primary":"5.0 megapixels","features":["Flash","Video"]},"additionalFeatures":"Front-Facing VGA Camera, Gorilla Glass Screen","images":[{"id":"580001","small":"http://www.google.com/phone/image/small/580001","medium":"http://www.google.com/phone/image/medium/580001"},{"id":"581001","small":"http://www.google.com/phone/image/small/581001","medium":"http://www.google.com/phone/image/medium/581001"},{"id":"582001","small":"http://www.google.com/phone/image/small/582001","medium":"http://www.google.com/phone/image/medium/582001"},{"id":"583001","small":"http://www.google.com/phone/image/small/583001","medium":"http://www.google.com/phone/image/medium/583001"},{"id":"584001","small":"http://www.google.com/phone/image/small/584001","medium":"http://www.google.com/phone/image/medium/584001"},{"id":"585001","small":"http://www.google.com/phone/image/small/585001","medium":"http://www.google.com/phone/image/medium/585001"}]}